[
    {
        "name": "Mùa yêu",
        "singer": "The Wall Nutszz",
        "source": "../../assets/songs/MuaYeu.mp3",
        "duration": "04:38",
        "thumbnail_desktop": "../../assets/thumbnails/desktop/MuaYeu_Desktop.jpg",
        "thumbnail_mobile": "../../assets/thumbnails/mobile/MuaYeu_Mobile.jpg",
        "updated": "14/03/2021"
    },
    {
        "name": "Suýt nữa thì",
        "singer": "Andiez",
        "source": "../../assets/songs/SuytNuaThi.mp3",
        "duration": "04:46",
        "thumbnail_desktop": "../../assets/thumbnails/desktop/SuytNuaThi_Desktop.jpg",
        "thumbnail_mobile": "../../assets/thumbnails/mobile/SuytNuaThi_Mobile.jpg",
        "updated": "03/04/2021"
    },
    {
        "name": "Love Story",
        "singer": "Tạ Anh Thắng",
        "source": "../../assets/songs/LoveStory.mp3",
        "duration": "04:13",
        "thumbnail_desktop": "../../assets/thumbnails/desktop/LoveStory_Desktop.jpg",
        "thumbnail_mobile": "../../assets/thumbnails/mobile/LoveStory_Mobile.jpg",
        "updated": "03/04/2021"
    },
    {
        "name": "Chờ đợi có đáng sợ",
        "singer": "Andiez",
        "source": "../../assets/songs/ChoDoiCoDangSo.mp3",
        "duration": "04:46",
        "thumbnail_desktop": "../../assets/thumbnails/desktop/ChoDoiCoDangSo_Desktop.jpg",
        "thumbnail_mobile": "../../assets/thumbnails/mobile/ChoDoiCoDangSo_Mobile.jpg",
        "updated": "14/03/2021"
    },
    {
        "name": "Gói những bông hoa nhỏ tặng em",
        "singer": "Kim chỉ Nam",
        "source": "../../assets/songs/GoiNhungBongHoaNhoTangEm.mp3",
        "duration": "04:51",
        "thumbnail_desktop": "../../assets/thumbnails/desktop/GoiNhungBongHoaNhoTangEm_Desktop.jpg",
        "thumbnail_mobile": "../../assets/thumbnails/mobile/GoiNhungBongHoaNhoTangEm_Mobile.jpg",
        "updated": "21/04/2021"
    },
    {
        "name": "Chúng mình cùng biết",
        "singer": "Naa",
        "source": "../../assets/songs/ChungMinhCungBiet.mp3",
        "duration": "02:27",
        "thumbnail_desktop": "../../assets/thumbnails/desktop/ChungMinhCungBiet_Desktop.jpg",
        "thumbnail_mobile": "../../assets/thumbnails/mobile/ChungMinhCungBiet_Mobile.jpg",
        "updated": "21/04/2021"
    },
    {
        "name": "Một mình ta",
        "singer": "BuiTruongLinh",
        "source": "../../assets/songs/MotMinhTa.mp3",
        "duration": "04:29",
        "thumbnail_desktop": "../../assets/thumbnails/desktop/MotMinhTa_Desktop.jpg",
        "thumbnail_mobile": "../../assets/thumbnails/mobile/MotMinhTa_Mobile.jpg",
        "updated": "21/04/2021"
    },
    {
        "name": "Giọt nắng bên thềm",
        "singer": "Anh Khang",
        "source": "../../assets/songs/GiotNangBenThem.mp3",
        "duration": "05:27",
        "thumbnail_desktop": "../../assets/thumbnails/desktop/GiotNangBenThem_Desktop.jpg",
        "thumbnail_mobile": "../../assets/thumbnails/mobile/GiotNangBenThem_Mobile.jpg",
        "updated": "21/04/2021"
    },
    {
        "name": "Chờ đến bao giờ",
        "singer": "Bệt Band",
        "source": "../../assets/songs/ChoDenBaoGio.mp3",
        "duration": "02:28",
        "thumbnail_desktop": "../../assets/thumbnails/desktop/ChoDenBaoGio_Desktop.jpg",
        "thumbnail_mobile": "../../assets/thumbnails/mobile/ChoDenBaoGio_Mobile.jpg",
        "updated": "14/03/2021"
    },
    {
        "name": "Chuyện mưa",
        "singer": "Trung Quân",
        "source": "../../assets/songs/ChuyenMua.mp3",
        "duration": "04:19",
        "thumbnail_desktop": "../../assets/thumbnails/desktop/ChuyenMua_Desktop.jpg",
        "thumbnail_mobile": "../../assets/thumbnails/mobile/ChuyenMua_Mobile.jpg",
        "updated": "14/03/2021"
    },
    {
        "name": "Đủ xa tình sẽ cũ",
        "singer": "JSOL",
        "source": "../../assets/songs/DuXaTinhSeCu.mp3",
        "duration": "04:08",
        "thumbnail_desktop": "../../assets/thumbnails/desktop/DuXaTinhSeCu_Desktop.jpg",
        "thumbnail_mobile": "../../assets/thumbnails/mobile/DuXaTinhSeCu_Mobile.jpg",
        "updated": "14/03/2021"
    },
    {
        "name": "Em ổn không",
        "singer": "Trịnh Thiên Ân",
        "source": "../../assets/songs/EmOnKhong.mp3",
        "duration": "05:19",
        "thumbnail_desktop": "../../assets/thumbnails/desktop/EmOnKhong_Desktop.jpg",
        "thumbnail_mobile": "../../assets/thumbnails/mobile/EmOnKhong_Mobile.jpg",
        "updated": "14/03/2021"
    },
    {
        "name": "Mãi mãi sẽ hết vào ngày mai",
        "singer": "Andiez",
        "source": "../../assets/songs/MaiMaiSeHetVaoNgayMai.mp3",
        "duration": "04:53",
        "thumbnail_desktop": "../../assets/thumbnails/desktop/MaiMaiSeHetVaoNgayMai_Desktop.jpg",
        "thumbnail_mobile": "../../assets/thumbnails/mobile/MaiMaiSeHetVaoNgayMai_Mobile.jpg",
        "updated": "14/03/2021"
    },
    {
        "name": "Mưa trên cuộc tình",
        "singer": "Edward Duong Nguyen",
        "source": "../../assets/songs/MuaTrenCuocTinh.mp3",
        "duration": "05:42",
        "thumbnail_desktop": "../../assets/thumbnails/desktop/MuaTrenCuocTinh_Desktop.jpg",
        "thumbnail_mobile": "../../assets/thumbnails/mobile/MuaTrenCuocTinh_Mobile.jpg",
        "updated": "14/03/2021"
    },
    {
        "name": "Thu Vội",
        "singer": "Valenine",
        "source": "../../assets/songs/ThuVoi.mp3",
        "duration": "04:22",
        "thumbnail_desktop": "../../assets/thumbnails/desktop/ThuVoi_Desktop.jpg",
        "thumbnail_mobile": "../../assets/thumbnails/mobile/ThuVoi_Mobile.jpg",
        "updated": "24/03/2021"
    },
    {
        "name": "Giá như em nhìn lại",
        "singer": "JSOL",
        "source": "../../assets/songs/GiaNhuEmNhinLai.mp3",
        "duration": "05:27",
        "thumbnail_desktop": "../../assets/thumbnails/desktop/GiaNhuEmNhinLai_Desktop.jpg",
        "thumbnail_mobile": "../../assets/thumbnails/mobile/GiaNhuEmNhinLai_Mobile.jpg",
        "updated": "24/03/2021"
    },
    {
        "name": "Không cần",
        "singer": "the SHEEP",
        "source": "../../assets/songs/KhongCan.mp3",
        "duration": "03:45",
        "thumbnail_desktop": "../../assets/thumbnails/desktop/KhongCan_Desktop.jpg",
        "thumbnail_mobile": "../../assets/thumbnails/mobile/KhongCan_Mobile.jpg",
        "updated": "02/04/2021"
    },
    {
        "name": "Thuận theo ý trời",
        "singer": "Bùi Anh Tuấn",
        "source": "../../assets/songs/ThuanTheoYTroi.mp3",
        "duration": "03:57",
        "thumbnail_desktop": "../../assets/thumbnails/desktop/ThuanTheoYTroi_Desktop.jpg",
        "thumbnail_mobile": "../../assets/thumbnails/mobile/ThuanTheoYTroi_Mobile.jpg",
        "updated": "02/04/2021"
    },
    {
        "name": "Không sao mà em đây rồi",
        "singer": "SUNI HẠ LINH ft Lou Hoàng",
        "source": "../../assets/songs/KhongSaoMaEmDayRoi.mp3",
        "duration": "04:24",
        "thumbnail_desktop": "../../assets/thumbnails/desktop/KhongSaoMaEmDayRoi_Desktop.jpg",
        "thumbnail_mobile": "../../assets/thumbnails/mobile/KhongSaoMaEmDayRoi_Mobile.jpg",
        "updated": "02/04/2021"
    },
    {
        "name": "Mãi chẳng thuộc về nhau",
        "singer": "Bozitt",
        "source": "../../assets/songs/MaiChangThuocVeNhau.mp3",
        "duration": "06:21",
        "thumbnail_desktop": "../../assets/thumbnails/desktop/MaiChangThuocVeNhau_Desktop.jpg",
        "thumbnail_mobile": "../../assets/thumbnails/mobile/MaiChangThuocVeNhau_Mobile.jpg",
        "updated": "02/04/2021"
    },
    {
        "name": "Phố đã lên đèn",
        "singer": "Huyền Tâm Môn",
        "source": "../../assets/songs/PhoDaLenDen.mp3",
        "duration": "04:41",
        "thumbnail_desktop": "../../assets/thumbnails/desktop/PhoDaLenDen_Desktop.jpg",
        "thumbnail_mobile": "../../assets/thumbnails/mobile/PhoDaLenDen_Mobile.jpg",
        "updated": "02/04/2021"
    },
    {
        "name": "Độ đúng đời",
        "singer": "THANH HƯNG ft. ĐỘ MIXI",
        "source": "../../assets/songs/DoDungDoi.mp3",
        "duration": "03:21",
        "thumbnail_desktop": "../../assets/thumbnails/desktop/DoDungDoi_Desktop.jpg",
        "thumbnail_mobile": "../../assets/thumbnails/mobile/DoDungDoi_Mobile.jpg",
        "updated": "02/04/2021"
    },
    {
        "name": "Nợ ai đó lời xin lỗi",
        "singer": "Bozitt",
        "source": "../../assets/songs/NoAiDoLoiXinLoi.mp3",
        "duration": "05:37",
        "thumbnail_desktop": "../../assets/thumbnails/desktop/NoAiDoLoiXinLoi_Desktop.jpg",
        "thumbnail_mobile": "../../assets/thumbnails/mobile/NoAiDoLoiXinLoi_Mobile.jpg",
        "updated": "02/04/2021"
    },
    {
        "name": "Kẻ mộng mơ",
        "singer": "Reddy",
        "source": "../../assets/songs/KeMongMo.mp3",
        "duration": "06:00",
        "thumbnail_desktop": "../../assets/thumbnails/desktop/KeMongMo_Desktop.jpg",
        "thumbnail_mobile": "../../assets/thumbnails/mobile/KeMongMo_Mobile.jpg",
        "updated": "02/04/2021"
    },
    {
        "name": "Về với anh đi",
        "singer": "Nguyễn Quang Quý",
        "source": "../../assets/songs/VeVoiAnhDi.mp3",
        "duration": "05:11",
        "thumbnail_desktop": "../../assets/thumbnails/desktop/VeVoiAnhDi_Desktop.jpg",
        "thumbnail_mobile": "../../assets/thumbnails/mobile/VeVoiAnhDi_Mobile.jpg",
        "updated": "02/04/2021"
    },
    {
        "name": "Anh mệt rồi",
        "singer": "Anh Quân Idol",
        "source": "../../assets/songs/AnhMetRoi.mp3",
        "duration": "04:57",
        "thumbnail_desktop": "../../assets/thumbnails/desktop/AnhMetRoi_Desktop.jpg",
        "thumbnail_mobile": "../../assets/thumbnails/mobile/AnhMetRoi_Mobile.jpg",
        "updated": "02/04/2021"
    },
    {
        "name": "Là ai mang nắng đi xa",
        "singer": "Yang",
        "source": "../../assets/songs/LaAiMangNangDiXa.mp3",
        "duration": "06:11",
        "thumbnail_desktop": "../../assets/thumbnails/desktop/LaAiMangNangDiXa_Desktop.jpg",
        "thumbnail_mobile": "../../assets/thumbnails/mobile/LaAiMangNangDiXa_Mobile.jpg",
        "updated": "02/04/2021"
    },
    {
        "name": "Chẳng thể tìm được em",
        "singer": "PhucXp",
        "source": "../../assets/songs/ChangTheTimDuocEm.mp3",
        "duration": "06:50",
        "thumbnail_desktop": "../../assets/thumbnails/desktop/ChangTheTimDuocEm_Desktop.jpg",
        "thumbnail_mobile": "../../assets/thumbnails/mobile/ChangTheTimDuocEm_Mobile.jpg",
        "updated": "02/04/2021"
    },
    {
        "name": "Mùa yêu đầu",
        "singer": "Đinh Mạnh Ninh",
        "source": "../../assets/songs/MuaYeuDau.mp3",
        "duration": "04:28",
        "thumbnail_desktop": "../../assets/thumbnails/desktop/MuaYeuDau_Desktop.jpg",
        "thumbnail_mobile": "../../assets/thumbnails/mobile/MuaYeuDau_Mobile.jpg",
        "updated": "02/04/2021"
    },
    {
        "name": "Gác lại âu lo",
        "singer": "Da LAB ft. Miu Lê",
        "source": "../../assets/songs/GacLaiAuLo.mp3",
        "duration": "04:34",
        "thumbnail_desktop": "../../assets/thumbnails/desktop/GacLaiAuLo_Desktop.jpg",
        "thumbnail_mobile": "../../assets/thumbnails/mobile/GacLaiAuLo_Mobile.jpg",
        "updated": "02/04/2021"
    },
    {
        "name": "Hương ngọc lan",
        "singer": "Thiếu Nữ Band",
        "source": "../../assets/songs/HuongNgocLan.mp3",
        "duration": "05:21",
        "thumbnail_desktop": "../../assets/thumbnails/desktop/HuongNgocLan_Desktop.jpg",
        "thumbnail_mobile": "../../assets/thumbnails/mobile/HuongNgocLan_Mobile.jpg",
        "updated": "02/04/2021"
    },
    {
        "name": "Có anh ở đây rồi",
        "singer": "Anh Quân Idol",
        "source": "../../assets/songs/CoAnhODayRoi.mp3",
        "duration": "04:52",
        "thumbnail_desktop": "../../assets/thumbnails/desktop/CoAnhODayRoi_Desktop.jpg",
        "thumbnail_mobile": "../../assets/thumbnails/mobile/CoAnhODayRoi_Mobile.jpg",
        "updated": "02/04/2021"
    },
    {
        "name": "Anh sẽ tốt mà",
        "singer": "Thùy Chi ft. Phạm Hồng Phước",
        "source": "../../assets/songs/AnhSeTotMa.mp3",
        "duration": "04:57",
        "thumbnail_desktop": "../../assets/thumbnails/desktop/AnhSeTotMa_Desktop.jpg",
        "thumbnail_mobile": "../../assets/thumbnails/mobile/AnhSeTotMa_Mobile.jpg",
        "updated": "02/04/2021"
    },
    {
        "name": "Beautiful Girl",
        "singer": "SKULL & HAHA",
        "source": "../../assets/songs/BeautifulGirl.mp3",
        "duration": "04:02",
        "thumbnail_desktop": "../../assets/thumbnails/desktop/BeautifulGirl_Desktop.jpg",
        "thumbnail_mobile": "../../assets/thumbnails/mobile/BeautifulGirl_Mobile.jpg",
        "updated": "02/04/2021"
    },
    {
        "name": "Chẳng nói nên lời",
        "singer": "Nguyễn Hoàng Dũng",
        "source": "../../assets/songs/ChangNoiNenLoi.mp3",
        "duration": "05:29",
        "thumbnail_desktop": "../../assets/thumbnails/desktop/ChangNoiNenLoi_Desktop.jpg",
        "thumbnail_mobile": "../../assets/thumbnails/mobile/ChangNoiNenLoi_Mobile.jpg",
        "updated": "02/04/2021"
    },
    {
        "name": "Dù có cách xa",
        "singer": "Đinh Mạnh Ninh",
        "source": "../../assets/songs/DuCoCachXa.mp3",
        "duration": "04:08",
        "thumbnail_desktop": "../../assets/thumbnails/desktop/DuCoCachXa_Desktop.jpg",
        "thumbnail_mobile": "../../assets/thumbnails/mobile/DuCoCachXa_Mobile.jpg",
        "updated": "02/04/2021"
    },
    {
        "name": "Say you do",
        "singer": "Tiên Tiên",
        "source": "../../assets/songs/SayYouDo.mp3",
        "duration": "03:41",
        "thumbnail_desktop": "../../assets/thumbnails/desktop/SayYouDo_Desktop.jpg",
        "thumbnail_mobile": "../../assets/thumbnails/mobile/SayYouDo_Mobile.jpg",
        "updated": "02/04/2021"
    },
    {
        "name": "Nơi này có anh",
        "singer": "Sơn Tùng M-TP",
        "source": "../../assets/songs/NoiNayCoAnh.mp3",
        "duration": "04:20",
        "thumbnail_desktop": "../../assets/thumbnails/desktop/NoiNayCoAnh_Desktop.jpg",
        "thumbnail_mobile": "../../assets/thumbnails/mobile/NoiNayCoAnh_Mobile.jpg",
        "updated": "02/04/2021"
    },
    {
        "name": "Lạc nhau có phải muôn đời",
        "singer": "Erik",
        "source": "../../assets/songs/LacNhauCoPhaiMuonDoi.mp3",
        "duration": "04:43",
        "thumbnail_desktop": "../../assets/thumbnails/desktop/LacNhauCoPhaiMuonDoi_Desktop.jpg",
        "thumbnail_mobile": "../../assets/thumbnails/mobile/LacNhauCoPhaiMuonDoi_Mobile.jpg",
        "updated": "02/04/2021"
    },
    {
        "name": "Cưới nhau đi",
        "singer": "Bùi Anh Tuấn , Hiền Hồ",
        "source": "../../assets/songs/CuoiNhauDi.mp3",
        "duration": "04:10",
        "thumbnail_desktop": "../../assets/thumbnails/desktop/CuoiNhauDi_Desktop.jpg",
        "thumbnail_mobile": "../../assets/thumbnails/mobile/CuoiNhauDi_Mobile.jpg",
        "updated": "02/04/2021"
    },
    {
        "name": "I do",
        "singer": "911",
        "source": "../../assets/songs/IDo.mp3",
        "duration": "03:28",
        "thumbnail_desktop": "../../assets/thumbnails/desktop/IDo_Desktop.jpg",
        "thumbnail_mobile": "../../assets/thumbnails/mobile/IDo_Mobile.jpg",
        "updated": "02/04/2021"
    },
    {
        "name": "Em không sai, chúng ta sai",
        "singer": "Erik",
        "source": "../../assets/songs/EmKhongSaiChungTaSai.mp3",
        "duration": "04:46",
        "thumbnail_desktop": "../../assets/thumbnails/desktop/EmKhongSaiChungTaSai_Desktop.jpg",
        "thumbnail_mobile": "../../assets/thumbnails/mobile/EmKhongSaiChungTaSai_Mobile.jpg",
        "updated": "02/04/2021"
    },
    {
        "name": "Nàng thơ",
        "singer": "Nguyễn Hoàng Dũng",
        "source": "../../assets/songs/NangTho.mp3",
        "duration": "04:15",
        "thumbnail_desktop": "../../assets/thumbnails/desktop/NangTho_Desktop.jpg",
        "thumbnail_mobile": "../../assets/thumbnails/mobile/NangTho_Mobile.jpg",
        "updated": "02/04/2021"
    },
    {
        "name": "Những gì anh nói",
        "singer": "Bozitt",
        "source": "../../assets/songs/NhungGiAnhNoi.mp3",
        "duration": "06:15",
        "thumbnail_desktop": "../../assets/thumbnails/desktop/NhungGiAnhNoi_Desktop.jpg",
        "thumbnail_mobile": "../../assets/thumbnails/mobile/NhungGiAnhNoi_Mobile.jpg",
        "updated": "02/04/2021"
    },
    {
        "name": "Em có nghe",
        "singer": "Kha",
        "source": "../../assets/songs/EmCoNghe.mp3",
        "duration": "04:05",
        "thumbnail_desktop": "../../assets/thumbnails/desktop/EmCoNghe_Desktop.jpg",
        "thumbnail_mobile": "../../assets/thumbnails/mobile/EmCoNghe_Mobile.jpg",
        "updated": "02/04/2021"
    },
    {
        "name": "Happy ending",
        "singer": "Erik",
        "source": "../../assets/songs/HappyEnding.mp3",
        "duration": "04:13",
        "thumbnail_desktop": "../../assets/thumbnails/desktop/HappyEnding_Desktop.jpg",
        "thumbnail_mobile": "../../assets/thumbnails/mobile/HappyEnding_Mobile.jpg",
        "updated": "02/04/2021"
    },
    {
        "name": "Missing you",
        "singer": "Hoàng Nhi",
        "source": "../../assets/songs/MissingYou.mp3",
        "duration": "04:08",
        "thumbnail_desktop": "../../assets/thumbnails/desktop/Default_Desktop.jpg",
        "thumbnail_mobile": "../../assets/thumbnails/mobile/Default_Mobile.jpg",
        "updated": "02/04/2021"
    },
    {
        "name": "Chuyện rằng",
        "singer": "Thịnh Suy",
        "source": "../../assets/songs/ChuyenRang.mp3",
        "duration": "04:35",
        "thumbnail_desktop": "../../assets/thumbnails/desktop/ChuyenRang_Desktop.jpg",
        "thumbnail_mobile": "../../assets/thumbnails/mobile/ChuyenRang_Mobile.jpg",
        "updated": "02/04/2021"
    },
    {
        "name": "Cups",
        "singer": "Anna Kendrick",
        "source": "../../assets/songs/Cups.mp3",
        "duration": "02:11",
        "thumbnail_desktop": "../../assets/thumbnails/desktop/Cups_Desktop.jpg",
        "thumbnail_mobile": "../../assets/thumbnails/mobile/Cups_Mobile.jpg",
        "updated": "02/04/2021"
    },
    {
        "name": "Cũng đành thôi",
        "singer": "Đức Phúc",
        "source": "../../assets/songs/CungDanhThoi.mp3",
        "duration": "04:32",
        "thumbnail_desktop": "../../assets/thumbnails/desktop/CungDanhThoi_Desktop.jpg",
        "thumbnail_mobile": "../../assets/thumbnails/mobile/CungDanhThoi_Mobile.jpg",
        "updated": "02/04/2021"
    },
    {
        "name": "Em của quá khứ",
        "singer": "Nguyễn Đình Vũ",
        "source": "../../assets/songs/EmCuaQuaKhu.mp3",
        "duration": "03:30",
        "thumbnail_desktop": "../../assets/thumbnails/desktop/EmCuaQuaKhu_Desktop.jpg",
        "thumbnail_mobile": "../../assets/thumbnails/mobile/EmCuaQuaKhu_Mobile.jpg",
        "updated": "02/04/2021"
    },
    {
        "name": "Mùa xa nhau",
        "singer": "Emily",
        "source": "../../assets/songs/MuaXaNhau.mp3",
        "duration": "04:34",
        "thumbnail_desktop": "../../assets/thumbnails/desktop/MuaXaNhau_Desktop.jpg",
        "thumbnail_mobile": "../../assets/thumbnails/mobile/MuaXaNhau_Mobile.jpg",
        "updated": "02/04/2021"
    },
    {
        "name": "Yêu được không",
        "singer": "Đức Phúc",
        "source": "../../assets/songs/YeuDuocKhong.mp3",
        "duration": "05:04",
        "thumbnail_desktop": "../../assets/thumbnails/desktop/YeuDuocKhong_Desktop.jpg",
        "thumbnail_mobile": "../../assets/thumbnails/mobile/YeuDuocKhong_Mobile.jpg",
        "updated": "03/04/2021"
    },
    {
        "name": "Dù chẳng phải anh",
        "singer": "Đinh Mạnh Ninh",
        "source": "../../assets/songs/DuChangPhaiAnh.mp3",
        "duration": "05:53",
        "thumbnail_desktop": "../../assets/thumbnails/desktop/DuChangPhaiAnh_Desktop.jpg",
        "thumbnail_mobile": "../../assets/thumbnails/mobile/DuChangPhaiAnh_Mobile.jpg",
        "updated": "03/04/2021"
    },
    {
        "name": "Màu nước mắt",
        "singer": "Nguyễn Trần Trung Quân",
        "source": "../../assets/songs/MauNuocMat.mp3",
        "duration": "05:37",
        "thumbnail_desktop": "../../assets/thumbnails/desktop/MauNuocMat_Desktop.jpg",
        "thumbnail_mobile": "../../assets/thumbnails/mobile/MauNuocMat_Mobile.jpg",
        "updated": "03/04/2021"
    },
    {
        "name": "Người con gái ta thương",
        "singer": "Hà Anh Tuấn",
        "source": "../../assets/songs/NguoiConGaiTaThuong.mp3",
        "duration": "06:27",
        "thumbnail_desktop": "../../assets/thumbnails/desktop/NguoiConGaiTaThuong_Desktop.jpg",
        "thumbnail_mobile": "../../assets/thumbnails/mobile/NguoiConGaiTaThuong_Mobile.jpg",
        "updated": "03/04/2021"
    },
    {
        "name": "Tình đắng như ly cà phê",
        "singer": "nân. x Ngơ",
        "source": "../../assets/songs/TinhDangNhuLyCaPhe.mp3",
        "duration": "03:35",
        "thumbnail_desktop": "../../assets/thumbnails/desktop/TinhDangNhuLyCaPhe_Desktop.jpg",
        "thumbnail_mobile": "../../assets/thumbnails/mobile/TinhDangNhuLyCaPhe_Mobile.jpg",
        "updated": "03/04/2021"
    },
    {
        "name": "Về phía mưa",
        "singer": "Thế Bảo",
        "source": "../../assets/songs/VePhiaMua.mp3",
        "duration": "05:36",
        "thumbnail_desktop": "../../assets/thumbnails/desktop/VePhiaMua_Desktop.jpg",
        "thumbnail_mobile": "../../assets/thumbnails/mobile/VePhiaMua_Mobile.jpg",
        "updated": "03/04/2021"
    },
    {
        "name": "Cuối chiều",
        "singer": "Hải Sâm",
        "source": "../../assets/songs/CuoiChieu.mp3",
        "duration": "03:50",
        "thumbnail_desktop": "../../assets/thumbnails/desktop/CuoiChieu_Desktop.jpg",
        "thumbnail_mobile": "../../assets/thumbnails/mobile/CuoiChieu_Mobile.jpg",
        "updated": "03/04/2021"
    },
    {
        "name": "Dù chỉ là",
        "singer": "Hoàng Chu ft. Tiến Thành",
        "source": "../../assets/songs/DuChiLa.mp3",
        "duration": "04:02",
        "thumbnail_desktop": "../../assets/thumbnails/desktop/DuChiLa_Desktop.jpg",
        "thumbnail_mobile": "../../assets/thumbnails/mobile/DuChiLa_Mobile.jpg",
        "updated": "03/04/2021"
    },
    {
        "name": "Giá như anh",
        "singer": "JayKii",
        "source": "../../assets/songs/GiaNhuAnh.mp3",
        "duration": "04:24",
        "thumbnail_desktop": "../../assets/thumbnails/desktop/GiaNhuAnh_Desktop.jpg",
        "thumbnail_mobile": "../../assets/thumbnails/mobile/GiaNhuAnh_Mobile.jpg",
        "updated": "03/04/2021"
    },
    {
        "name": "Hẹn một mai",
        "singer": "Bùi Anh Tuấn",
        "source": "../../assets/songs/HenMotMai.mp3",
        "duration": "04:43",
        "thumbnail_desktop": "../../assets/thumbnails/desktop/HenMotMai_Desktop.jpg",
        "thumbnail_mobile": "../../assets/thumbnails/mobile/HenMotMai_Mobile.jpg",
        "updated": "03/04/2021"
    },
    {
        "name": "Lạnh thôi đừng mưa",
        "singer": "Hải Sâm",
        "source": "../../assets/songs/LanhThoiDungMua.mp3",
        "duration": "04:24",
        "thumbnail_desktop": "../../assets/thumbnails/desktop/LanhThoiDungMua_Desktop.jpg",
        "thumbnail_mobile": "../../assets/thumbnails/mobile/LanhThoiDungMua_Mobile.jpg",
        "updated": "03/04/2021"
    },
    {
        "name": "Lạ lùng",
        "singer": "Vũ",
        "source": "../../assets/songs/LaLung.mp3",
        "duration": "04:21",
        "thumbnail_desktop": "../../assets/thumbnails/desktop/LaLung_Desktop.jpg",
        "thumbnail_mobile": "../../assets/thumbnails/mobile/LaLung_Mobile.jpg",
        "updated": "03/04/2021"
    },
    {
        "name": "Nhớ em",
        "singer": "Minh Vương M4U",
        "source": "../../assets/songs/NhoEm.mp3",
        "duration": "05:45",
        "thumbnail_desktop": "../../assets/thumbnails/desktop/NhoEm_Desktop.jpg",
        "thumbnail_mobile": "../../assets/thumbnails/mobile/NhoEm_Mobile.jpg",
        "updated": "03/04/2021"
    },
    {
        "name": "Phút ban đầu",
        "singer": "Vũ",
        "source": "../../assets/songs/PhutBanDau.mp3",
        "duration": "04:00",
        "thumbnail_desktop": "../../assets/thumbnails/desktop/PhutBanDau_Desktop.jpg",
        "thumbnail_mobile": "../../assets/thumbnails/mobile/PhutBanDau_Mobile.jpg",
        "updated": "03/04/2021"
    },
    {
        "name": "Thả vào mưa",
        "singer": "Trung Quân",
        "source": "../../assets/songs/ThaVaoMua.mp3",
        "duration": "05:44",
        "thumbnail_desktop": "../../assets/thumbnails/desktop/ThaVaoMua_Desktop.jpg",
        "thumbnail_mobile": "../../assets/thumbnails/mobile/ThaVaoMua_Mobile.jpg",
        "updated": "03/04/2021"
    },
    {
        "name": "Trời giấu trời mang đi",
        "singer": "Amee x Viruss",
        "source": "../../assets/songs/TroiGiauTroiMangDi.mp3",
        "duration": "04:13",
        "thumbnail_desktop": "../../assets/thumbnails/desktop/TroiGiauTroiMangDi_Desktop.jpg",
        "thumbnail_mobile": "../../assets/thumbnails/mobile/TroiGiauTroiMangDi_Mobile.jpg",
        "updated": "03/04/2021"
    },
    {
        "name": "Tình yêu chắp vá",
        "singer": "Mr Siro",
        "source": "../../assets/songs/TinhYeuChapVa.mp3",
        "duration": "04:42",
        "thumbnail_desktop": "../../assets/thumbnails/desktop/TinhYeuChapVa_Desktop.jpg",
        "thumbnail_mobile": "../../assets/thumbnails/mobile/TinhYeuChapVa_Mobile.jpg",
        "updated": "03/04/2021"
    },
    {
        "name": "Đừng lo anh đợi mà",
        "singer": "Mr Siro",
        "source": "../../assets/songs/DungLoAnhDoiMa.mp3",
        "duration": "04:47",
        "thumbnail_desktop": "../../assets/thumbnails/desktop/DungLoAnhDoiMa_Desktop.jpg",
        "thumbnail_mobile": "../../assets/thumbnails/mobile/DungLoAnhDoiMa_Mobile.jpg",
        "updated": "03/04/2021"
    },
    {
        "name": "3 1 0 7",
        "singer": "Duongg",
        "source": "../../assets/songs/3107.mp3",
        "duration": "02:39",
        "thumbnail_desktop": "../../assets/thumbnails/desktop/3107_Desktop.jpg",
        "thumbnail_mobile": "../../assets/thumbnails/mobile/3107_Mobile.jpg",
        "updated": "03/04/2021"
    },
    {
        "name": "Daydream",
        "singer": "Soobin Hoàng Sơn ft. BigDaddy",
        "source": "../../assets/songs/Daydreams.mp3",
        "duration": "04:53",
        "thumbnail_desktop": "../../assets/thumbnails/desktop/Default_Desktop.jpg",
        "thumbnail_mobile": "../../assets/thumbnails/mobile/Default_Mobile.jpg",
        "updated": "03/04/2021"
    },
    {
        "name": "Sài Gòn của anh",
        "singer": "HuyR, K-ICM",
        "source": "../../assets/songs/SaiGonCuaAnh.mp3",
        "duration": "04:32",
        "thumbnail_desktop": "../../assets/thumbnails/desktop/SaiGonCuaAnh_Desktop.jpg",
        "thumbnail_mobile": "../../assets/thumbnails/mobile/SaiGonCuaAnh_Mobile.jpg",
        "updated": "03/04/2021"
    },
    {
        "name": "Yêu em rất nhiều",
        "singer": "Hoàng Tôn",
        "source": "../../assets/songs/YeuEmRatNhieu.mp3",
        "duration": "04:33",
        "thumbnail_desktop": "../../assets/thumbnails/desktop/YeuEmRatNhieu_Desktop.jpg",
        "thumbnail_mobile": "../../assets/thumbnails/mobile/YeuEmRatNhieu_Mobile.jpg",
        "updated": "03/04/2021"
    },
    {
        "name": "Đồi hoa mặt trời",
        "singer": "Hoàng Yến Chibi",
        "source": "../../assets/songs/DoiHoaMatTroi.mp3",
        "duration": "04:01",
        "thumbnail_desktop": "../../assets/thumbnails/desktop/DoiHoaMatTroi_Desktop.jpg",
        "thumbnail_mobile": "../../assets/thumbnails/mobile/DoiHoaMatTroi_Mobile.jpg",
        "updated": "03/04/2021"
    },
    {
        "name": "Ta còn yêu nhau",
        "singer": "Đức Phúc",
        "source": "../../assets/songs/TaConYeuNhau.mp3",
        "duration": "03:27",
        "thumbnail_desktop": "../../assets/thumbnails/desktop/TaConYeuNhau_Desktop.jpg",
        "thumbnail_mobile": "../../assets/thumbnails/mobile/TaConYeuNhau_Mobile.jpg",
        "updated": "03/04/2021"
    },
    {
        "name": "Phía sau một cô gái",
        "singer": "SooBin Hoàng Sơn",
        "source": "../../assets/songs/PhiaSauMotCoGai.mp3",
        "duration": "04:28",
        "thumbnail_desktop": "../../assets/thumbnails/desktop/PhiaSauMotCoGai_Desktop.jpg",
        "thumbnail_mobile": "../../assets/thumbnails/mobile/PhiaSauMotCoGai_Mobile.jpg",
        "updated": "03/04/2021"
    },
    {
        "name": "Hôm nay tôi buồn",
        "singer": "Phùng Khánh Linh",
        "source": "../../assets/songs/HomNayToiBuon.mp3",
        "duration": "04:38",
        "thumbnail_desktop": "../../assets/thumbnails/desktop/HomNayToiBuon_Desktop.jpg",
        "thumbnail_mobile": "../../assets/thumbnails/mobile/HomNayToiBuon_Mobile.jpg",
        "updated": "03/04/2021"
    },
    {
        "name": "1 Phút",
        "singer": "Andiez",
        "source": "../../assets/songs/1Phut.mp3",
        "duration": "06:16",
        "thumbnail_desktop": "../../assets/thumbnails/desktop/1Phut_Desktop.jpg",
        "thumbnail_mobile": "../../assets/thumbnails/mobile/1Phut_Mobile.jpg",
        "updated": "03/04/2021"
    },
    {
        "name": "Anh không muốn bất công với em",
        "singer": "ACENS",
        "source": "../../assets/songs/AnhKhongMuonBatCongVoiEm.mp3",
        "duration": "03:23",
        "thumbnail_desktop": "../../assets/thumbnails/desktop/AnhKhongMuonBatCongVoiEm_Desktop.jpg",
        "thumbnail_mobile": "../../assets/thumbnails/mobile/AnhKhongMuonBatCongVoiEm_Mobile.jpg",
        "updated": "03/04/2021"
    },
    {
        "name": "Xe đạp",
        "singer": "Thùy Chi ft. M4U",
        "source": "../../assets/songs/XeDap.mp3",
        "duration": "05:03",
        "thumbnail_desktop": "../../assets/thumbnails/desktop/XeDap_Desktop.jpg",
        "thumbnail_mobile": "../../assets/thumbnails/mobile/XeDap_Mobile.jpg",
        "updated": "03/04/2021"
    },
    {
        "name": "Dòng thời gian",
        "singer": "Nguyễn Hải Phong",
        "source": "../../assets/songs/DongThoiGian.mp3",
        "duration": "05:06",
        "thumbnail_desktop": "../../assets/thumbnails/desktop/Default_Desktop.jpg",
        "thumbnail_mobile": "../../assets/thumbnails/mobile/Default_Mobile.jpg",
        "updated": "03/04/2021"
    },
    {
        "name": "Ba kể con nghe",
        "singer": "Dương Trần Nghĩa",
        "source": "../../assets/songs/BaKeConNghe.mp3",
        "duration": "06:19",
        "thumbnail_desktop": "../../assets/thumbnails/desktop/BaKeConNghe_Desktop.jpg",
        "thumbnail_mobile": "../../assets/thumbnails/mobile/BaKeConNghe_Mobile.jpg",
        "updated": "03/04/2021"
    },
    {
        "name": "Người tôi yêu",
        "singer": "Chi Dân",
        "source": "../../assets/songs/NguoiToiYeu.mp3",
        "duration": "04:21",
        "thumbnail_desktop": "../../assets/thumbnails/desktop/Default_Desktop.jpg",
        "thumbnail_mobile": "../../assets/thumbnails/mobile/Default_Mobile.jpg",
        "updated": "03/04/2021"
    },
    {
        "name": "Ánh nắng của anh",
        "singer": "Đức Phúc",
        "source": "../../assets/songs/AnhNangCuaAnh.mp3",
        "duration": "04:24",
        "thumbnail_desktop": "../../assets/thumbnails/desktop/AnhNangCuaAnh_Desktop.jpg",
        "thumbnail_mobile": "../../assets/thumbnails/mobile/AnhNangCuaAnh_Mobile.jpg",
        "updated": "03/04/2021"
    },
    {
        "name": "Bức tranh từ nước mắt",
        "singer": "Mr Siro",
        "source": "../../assets/songs/BucTranhTuNuocMat.mp3",
        "duration": "04:36",
        "thumbnail_desktop": "../../assets/thumbnails/desktop/BucTranhTuNuocMat_Desktop.jpg",
        "thumbnail_mobile": "../../assets/thumbnails/mobile/BucTranhTuNuocMat_Mobile.jpg",
        "updated": "03/04/2021"
    },
    {
        "name": "Day dứt nỗi đau",
        "singer": "Mr Siro",
        "source": "../../assets/songs/DayDutNoiDau.mp3",
        "duration": "05:15",
        "thumbnail_desktop": "../../assets/thumbnails/desktop/Default_Desktop.jpg",
        "thumbnail_mobile": "../../assets/thumbnails/mobile/Default_Mobile.jpg",
        "updated": "03/04/2021"
    },
    {
        "name": "Yêu lại từ đầu",
        "singer": "Khắc Việt",
        "source": "../../assets/songs/YeuLaiTuDau.mp3",
        "duration": "03:23",
        "thumbnail_desktop": "../../assets/thumbnails/desktop/YeuLaiTuDau_Desktop.jpg",
        "thumbnail_mobile": "../../assets/thumbnails/mobile/YeuLaiTuDau_Mobile.jpg",
        "updated": "03/04/2021"
    },
    {
        "name": "Gió vẫn hát",
        "singer": "Long Phạm",
        "source": "../../assets/songs/GioVanHat.mp3",
        "duration": "04:01",
        "thumbnail_desktop": "../../assets/thumbnails/desktop/GioVanHat_Desktop.jpg",
        "thumbnail_mobile": "../../assets/thumbnails/mobile/GioVanHat_Mobile.jpg",
        "updated": "03/04/2021"
    },
    {
        "name": "Sai người sai thời điểm",
        "singer": "Thanh Hưng",
        "source": "../../assets/songs/SaiNguoiSaiThoiDiem.mp3",
        "duration": "06:08",
        "thumbnail_desktop": "../../assets/thumbnails/desktop/SaiNguoiSaiThoiDiem_Desktop.jpg",
        "thumbnail_mobile": "../../assets/thumbnails/mobile/SaiNguoiSaiThoiDiem_Mobile.jpg",
        "updated": "03/04/2021"
    },
    {
        "name": "Đừng quên tên anh",
        "singer": "Hoa Vinh",
        "source": "../../assets/songs/DungQuenTenAnh.mp3",
        "duration": "05:48",
        "thumbnail_desktop": "../../assets/thumbnails/desktop/DungQuenTenAnh_Desktop.jpg",
        "thumbnail_mobile": "../../assets/thumbnails/mobile/DungQuenTenAnh_Mobile.jpg",
        "updated": "03/04/2021"
    },
    {
        "name": "Người ấy",
        "singer": "Trịnh Thăng Bình",
        "source": "../../assets/songs/NguoiAy.mp3",
        "duration": "04:21",
        "thumbnail_desktop": "../../assets/thumbnails/desktop/NguoiAy_Desktop.jpg",
        "thumbnail_mobile": "../../assets/thumbnails/mobile/NguoiAy_Mobile.jpg",
        "updated": "03/04/2021"
    },
    {
        "name": "Chờ anh nhé",
        "singer": "Hoàng Dũng, Hoàng Rob",
        "source": "../../assets/songs/ChoAnhNhe.mp3",
        "duration": "04:05",
        "thumbnail_desktop": "../../assets/thumbnails/desktop/ChoAnhNhe_Desktop.jpg",
        "thumbnail_mobile": "../../assets/thumbnails/mobile/ChoAnhNhe_Mobile.jpg",
        "updated": "03/04/2021"
    },
    {
        "name": "Yêu một người có lẽ",
        "singer": "Lou Hoàng ft Miu Lê",
        "source": "../../assets/songs/YeuMotNguoiCoLe.mp3",
        "duration": "04:20",
        "thumbnail_desktop": "../../assets/thumbnails/desktop/YeuMotNguoiCoLe_Desktop.jpg",
        "thumbnail_mobile": "../../assets/thumbnails/mobile/YeuMotNguoiCoLe_Mobile.jpg",
        "updated": "03/04/2021"
    },
    {
        "name": "Đếm ngày xa em",
        "singer": "OnlyC ft Lou Hoàng",
        "source": "../../assets/songs/DemNgayXaEm.mp3",
        "duration": "04:17",
        "thumbnail_desktop": "../../assets/thumbnails/desktop/DemNgayXaEm_Desktop.jpg",
        "thumbnail_mobile": "../../assets/thumbnails/mobile/DemNgayXaEm_Mobile.jpg",
        "updated": "03/04/2021"
    },
    {
        "name": "Thằng điên",
        "singer": "Justatee ft Phương Ly",
        "source": "../../assets/songs/ThangDien.mp3",
        "duration": "03:50",
        "thumbnail_desktop": "../../assets/thumbnails/desktop/ThangDien_Desktop.jpg",
        "thumbnail_mobile": "../../assets/thumbnails/mobile/ThangDien_Mobile.jpg",
        "updated": "03/04/2021"
    },
    {
        "name": "Lời yêu ngây dại",
        "singer": "Kha",
        "source": "../../assets/songs/LoiYeuNgayDai.mp3",
        "duration": "04:33",
        "thumbnail_desktop": "../../assets/thumbnails/desktop/Default_Desktop.jpg",
        "thumbnail_mobile": "../../assets/thumbnails/mobile/Default_Mobile.jpg",
        "updated": "03/04/2021"
    },
    {
        "name": "Hơn cả yêu",
        "singer": "Đức Phúc",
        "source": "../../assets/songs/HonCaYeu.mp3",
        "duration": "04:13",
        "thumbnail_desktop": "../../assets/thumbnails/desktop/HonCaYeu_Desktop.jpg",
        "thumbnail_mobile": "../../assets/thumbnails/mobile/HonCaYeu_Mobile.jpg",
        "updated": "03/04/2021"
    },
    {
        "name": "Chỉ anh hiểu em",
        "singer": "Khắc Việt",
        "source": "../../assets/songs/ChiAnhHieuEm.mp3",
        "duration": "04:29",
        "thumbnail_desktop": "../../assets/thumbnails/desktop/Default_Desktop.jpg",
        "thumbnail_mobile": "../../assets/thumbnails/mobile/Default_Mobile.jpg",
        "updated": "03/04/2021"
    },
    {
        "name": "Suy nghĩ trong anh",
        "singer": "Nam Cường ft Khắc Việt",
        "source": "../../assets/songs/SuyNghiTrongAnh.mp3",
        "duration": "05:10",
        "thumbnail_desktop": "../../assets/thumbnails/desktop/SuyNghiTrongAnh_Desktop.jpg",
        "thumbnail_mobile": "../../assets/thumbnails/mobile/SuyNghiTrongAnh_Mobile.jpg",
        "updated": "03/04/2021"
    },
    {
        "name": "Chuyện của mùa đông",
        "singer": "Tiến Thành",
        "source": "../../assets/songs/ChuyenCuaMuaDong.mp3",
        "duration": "06:00",
        "thumbnail_desktop": "../../assets/thumbnails/desktop/ChuyenCuaMuaDong_Desktop.jpg",
        "thumbnail_mobile": "../../assets/thumbnails/mobile/ChuyenCuaMuaDong_Mobile.jpg",
        "updated": "03/04/2021"
    },
    {
        "name": "Ừ có anh đây",
        "singer": "Tino",
        "source": "../../assets/songs/UCoAnhDay.mp3",
        "duration": "06:05",
        "thumbnail_desktop": "../../assets/thumbnails/desktop/UCoAnhDay_Desktop.jpg",
        "thumbnail_mobile": "../../assets/thumbnails/mobile/UCoAnhDay_Mobile.jpg",
        "updated": "03/04/2021"
    },
    {
        "name": "She neva knows",
        "singer": "JustaTee",
        "source": "../../assets/songs/SheNevaKnows.mp3",
        "duration": "04:47",
        "thumbnail_desktop": "../../assets/thumbnails/desktop/Default_Desktop.jpg",
        "thumbnail_mobile": "../../assets/thumbnails/mobile/Default_Mobile.jpg",
        "updated": "03/04/2021"
    },
    {
        "name": "Con đường tôi",
        "singer": "Trọng Hiếu",
        "source": "../../assets/songs/ConDuongToi.mp3",
        "duration": "03:28",
        "thumbnail_desktop": "../../assets/thumbnails/desktop/Default_Desktop.jpg",
        "thumbnail_mobile": "../../assets/thumbnails/mobile/Default_Mobile.jpg",
        "updated": "03/04/2021"
    },
    {
        "name": "Anh thương em nhất mà",
        "singer": "Lã. x Log x TiB",
        "source": "../../assets/songs/AnhThuongEmNhatMa.mp3",
        "duration": "03:14",
        "thumbnail_desktop": "../../assets/thumbnails/desktop/AnhThuongEmNhatMa_Desktop.jpg",
        "thumbnail_mobile": "../../assets/thumbnails/mobile/AnhThuongEmNhatMa_Mobile.jpg",
        "updated": "03/04/2021"
    },
    {
        "name": "Ngày gặp em",
        "singer": "TAT",
        "source": "../../assets/songs/NgayGapEm.mp3",
        "duration": "04:30",
        "thumbnail_desktop": "../../assets/thumbnails/desktop/NgayGapEm_Desktop.jpg",
        "thumbnail_mobile": "../../assets/thumbnails/mobile/NgayGapEm_Mobile.jpg",
        "updated": "03/04/2021"
    },
    {
        "name": "Điều kết thúc",
        "singer": "Alex Lâm",
        "source": "../../assets/songs/DieuKetThuc.mp3",
        "duration": "05:04",
        "thumbnail_desktop": "../../assets/thumbnails/desktop/DieuKetThuc_Desktop.jpg",
        "thumbnail_mobile": "../../assets/thumbnails/mobile/DieuKetThuc_Mobile.jpg",
        "updated": "03/04/2021"
    },
    {
        "name": "Vài giây nữa thôi",
        "singer": "Reddy",
        "source": "../../assets/songs/VaiGiayNuaThoi.mp3",
        "duration": "04:41",
        "thumbnail_desktop": "../../assets/thumbnails/desktop/VaiGiayNuaThoi_Desktop.jpg",
        "thumbnail_mobile": "../../assets/thumbnails/mobile/VaiGiayNuaThoi_Mobile.jpg",
        "updated": "03/04/2021"
    },
    {
        "name": "Gửi",
        "singer": "Reddy",
        "source": "../../assets/songs/Gui.mp3",
        "duration": "05:09",
        "thumbnail_desktop": "../../assets/thumbnails/desktop/Gui_Desktop.jpg",
        "thumbnail_mobile": "../../assets/thumbnails/mobile/Gui_Mobile.jpg",
        "updated": "03/04/2021"
    },
    {
        "name": "Nếu một ngày",
        "singer": "Reddy",
        "source": "../../assets/songs/NeuMotNgay.mp3",
        "duration": "04:55",
        "thumbnail_desktop": "../../assets/thumbnails/desktop/NeuMotNgay_Desktop.jpg",
        "thumbnail_mobile": "../../assets/thumbnails/mobile/NeuMotNgay_Mobile.jpg",
        "updated": "03/04/2021"
    },
    {
        "name": "Sợ",
        "singer": "Reddy",
        "source": "../../assets/songs/So.mp3",
        "duration": "04:11",
        "thumbnail_desktop": "../../assets/thumbnails/desktop/So_Desktop.jpg",
        "thumbnail_mobile": "../../assets/thumbnails/mobile/So_Mobile.jpg",
        "updated": "03/04/2021"
    },
    {
        "name": "Thì thôi",
        "singer": "Reddy",
        "source": "../../assets/songs/ThiThoi.mp3",
        "duration": "05:56",
        "thumbnail_desktop": "../../assets/thumbnails/desktop/ThiThoi_Desktop.jpg",
        "thumbnail_mobile": "../../assets/thumbnails/mobile/ThiThoi_Mobile.jpg",
        "updated": "03/04/2021"
    },
    {
        "name": "Thời thanh xuân sẽ qua",
        "singer": "Phạm Hồng Phước ft. Văn Mai Hương",
        "source": "../../assets/songs/ThoiThanhXuanSeQua.mp3",
        "duration": "06:51",
        "thumbnail_desktop": "../../assets/thumbnails/desktop/ThoiThanhXuanSeQua_Desktop.jpg",
        "thumbnail_mobile": "../../assets/thumbnails/mobile/ThoiThanhXuanSeQua_Mobile.jpg",
        "updated": "03/04/2021"
    },
    {
        "name": "Ngày xưa em đến",
        "singer": "Anh Khang",
        "source": "../../assets/songs/NgayXuaEmDen.mp3",
        "duration": "04:18",
        "thumbnail_desktop": "../../assets/thumbnails/desktop/NgayXuaEmDen_Desktop.jpg",
        "thumbnail_mobile": "../../assets/thumbnails/mobile/NgayXuaEmDen_Mobile.jpg",
        "updated": "03/04/2021"
    },
    {
        "name": "Anh mơ",
        "singer": "Anh Khang",
        "source": "../../assets/songs/AnhMo.mp3",
        "duration": "04:24",
        "thumbnail_desktop": "../../assets/thumbnails/desktop/AnhMo_Desktop.jpg",
        "thumbnail_mobile": "../../assets/thumbnails/mobile/AnhMo_Mobile.jpg",
        "updated": "03/04/2021"
    },
    {
        "name": "Way back home",
        "singer": "SHAUN",
        "source": "../../assets/songs/WayBackHome.mp3",
        "duration": "03:42",
        "thumbnail_desktop": "../../assets/thumbnails/desktop/WayBackHome_Desktop.jpg",
        "thumbnail_mobile": "../../assets/thumbnails/mobile/WayBackHome_Mobile.jpg",
        "updated": "03/04/2021"
    },
    {
        "name": "Chẳng để em xa anh",
        "singer": "Đức Phúc",
        "source": "../../assets/songs/ChangDeEmXaAnh.mp3",
        "duration": "04:23",
        "thumbnail_desktop": "../../assets/thumbnails/desktop/ChangDeEmXaAnh_Desktop.jpg",
        "thumbnail_mobile": "../../assets/thumbnails/mobile/ChangDeEmXaAnh_Mobile.jpg",
        "updated": "03/04/2021"
    },
    {
        "name": "Tớ thích cậu nhường nào rồi cậu sẽ biết thôi",
        "singer": "Hồ Nhất Thiên",
        "source": "../../assets/songs/ToThichCauNhuongNaoRoiCauSeBietThoi.mp3",
        "duration": "03:48",
        "thumbnail_desktop": "../../assets/thumbnails/desktop/ToThichCauNhuongNaoRoiCauSeBietThoi_Desktop.jpg",
        "thumbnail_mobile": "../../assets/thumbnails/mobile/ToThichCauNhuongNaoRoiCauSeBietThoi_Mobile.jpg",
        "updated": "03/04/2021"
    },
    {
        "name": "Cafe, thuốc lá & Những ngày vui",
        "singer": "Thế Bảo",
        "source": "../../assets/songs/CafeThuocLaVaNhungNgayVui.mp3",
        "duration": "05:27",
        "thumbnail_desktop": "../../assets/thumbnails/desktop/CafeThuocLaVaNhungNgayVui_Desktop.jpg",
        "thumbnail_mobile": "../../assets/thumbnails/mobile/CafeThuocLaVaNhungNgayVui_Mobile.jpg",
        "updated": "03/04/2021"
    },
    {
        "name": "Tự lau nước mắt",
        "singer": "Mr Siro",
        "source": "../../assets/songs/TuLauNuocMat.mp3",
        "duration": "05:23",
        "thumbnail_desktop": "../../assets/thumbnails/desktop/TuLauNuocMat_Desktop.jpg",
        "thumbnail_mobile": "../../assets/thumbnails/mobile/TuLauNuocMat_Mobile.jpg",
        "updated": "03/04/2021"
    },
    {
        "name": "Một đêm say",
        "singer": "Thịnh Suy",
        "source": "../../assets/songs/MotDemSay.mp3",
        "duration": "04:22",
        "thumbnail_desktop": "../../assets/thumbnails/desktop/Default_Desktop.jpg",
        "thumbnail_mobile": "../../assets/thumbnails/mobile/Default_Mobile.jpg",
        "updated": "03/04/2021"
    },
    {
        "name": "Với anh em vẫn là cô bé",
        "singer": "Xuân Hiển",
        "source": "../../assets/songs/VoiAnhEmVanLaCoBe.mp3",
        "duration": "04:51",
        "thumbnail_desktop": "../../assets/thumbnails/desktop/Default_Desktop.jpg",
        "thumbnail_mobile": "../../assets/thumbnails/mobile/Default_Mobile.jpg",
        "updated": "03/04/2021"
    },
    {
        "name": "Xin lỗi anh yêu em",
        "singer": "Xuân Hiển",
        "source": "../../assets/songs/XinLoiAnhYeuEm.mp3",
        "duration": "05:52",
        "thumbnail_desktop": "../../assets/thumbnails/desktop/Default_Desktop.jpg",
        "thumbnail_mobile": "../../assets/thumbnails/mobile/Default_Mobile.jpg",
        "updated": "03/04/2021"
    },
    {
        "name": "Gương mặt lạ lẫm",
        "singer": "Mr Siro",
        "source": "../../assets/songs/GuongMatLaLam.mp3",
        "duration": "05:42",
        "thumbnail_desktop": "../../assets/thumbnails/desktop/Default_Desktop.jpg",
        "thumbnail_mobile": "../../assets/thumbnails/mobile/Default_Mobile.jpg",
        "updated": "03/04/2021"
    },
    {
        "name": "Cô gái m52",
        "singer": "HuyR ft. Tùng Viu",
        "source": "../../assets/songs/CoGaiM52.mp3",
        "duration": "03:31",
        "thumbnail_desktop": "../../assets/thumbnails/desktop/CoGaiM52_Desktop.jpg",
        "thumbnail_mobile": "../../assets/thumbnails/mobile/CoGaiM52_Mobile.jpg",
        "updated": "03/04/2021"
    },
    {
        "name": "Thấy là yêu thương",
        "singer": "Only C",
        "source": "../../assets/songs/ThayLaYeuThuong.mp3",
        "duration": "04:01",
        "thumbnail_desktop": "../../assets/thumbnails/desktop/ThayLaYeuThuong_Desktop.jpg",
        "thumbnail_mobile": "../../assets/thumbnails/mobile/ThayLaYeuThuong_Mobile.jpg",
        "updated": "03/04/2021"
    },
    {
        "name": "Khi người lớn cô đơn",
        "singer": "Phạm Hồng Phước",
        "source": "../../assets/songs/KhiNguoiLonCoDon.mp3",
        "duration": "05:46",
        "thumbnail_desktop": "../../assets/thumbnails/desktop/KhiNguoiLonCoDon_Desktop.jpg",
        "thumbnail_mobile": "../../assets/thumbnails/mobile/KhiNguoiLonCoDon_Mobile.jpg",
        "updated": "03/04/2021"
    },
    {
        "name": "Tình yêu chậm trễ",
        "singer": "MONSTAR",
        "source": "../../assets/songs/TinhYeuChamTre.mp3",
        "duration": "03:47",
        "thumbnail_desktop": "../../assets/thumbnails/desktop/TinhYeuChamTre_Desktop.jpg",
        "thumbnail_mobile": "../../assets/thumbnails/mobile/TinhYeuChamTre_Mobile.jpg",
        "updated": "03/04/2021"
    },
    {
        "name": "Đã lỡ yêu em nhiều",
        "singer": "JustaTee",
        "source": "../../assets/songs/DaLoYeuEmNhieu.mp3",
        "duration": "04:30",
        "thumbnail_desktop": "../../assets/thumbnails/desktop/DaLoYeuEmNhieu_Desktop.jpg",
        "thumbnail_mobile": "../../assets/thumbnails/mobile/DaLoYeuEmNhieu_Mobile.jpg",
        "updated": "03/04/2021"
    },
    {
        "name": "Em dạo này",
        "singer": "Ngọt",
        "source": "../../assets/songs/EmDaoNay.mp3",
        "duration": "04:13",
        "thumbnail_desktop": "../../assets/thumbnails/desktop/EmDaoNay_Desktop.jpg",
        "thumbnail_mobile": "../../assets/thumbnails/mobile/EmDaoNay_Mobile.jpg",
        "updated": "03/04/2021"
    },
    {
        "name": "Ta quên nhau chưa",
        "singer": "Juun Đăng Dũng ft. R.Tee",
        "source": "../../assets/songs/TaQuenNhauChua.mp3",
        "duration": "03:49",
        "thumbnail_desktop": "../../assets/thumbnails/desktop/TaQuenNhauChua_Desktop.jpg",
        "thumbnail_mobile": "../../assets/thumbnails/mobile/TaQuenNhauChua_Mobile.jpg",
        "updated": "03/04/2021"
    },
    {
        "name": "The Scientist",
        "singer": "Holly Henry",
        "source": "../../assets/songs/TheScientist.mp3",
        "duration": "03:36",
        "thumbnail_desktop": "../../assets/thumbnails/desktop/Default_Desktop.jpg",
        "thumbnail_mobile": "../../assets/thumbnails/mobile/Default_Mobile.jpg",
        "updated": "03/04/2021"
    },
    {
        "name": "Yêu là 'Tha Thu'",
        "singer": "OnlyC",
        "source": "../../assets/songs/YeuLaThaThu.mp3",
        "duration": "04:33",
        "thumbnail_desktop": "../../assets/thumbnails/desktop/YeuLaThaThu_Desktop.jpg",
        "thumbnail_mobile": "../../assets/thumbnails/mobile/YeuLaThaThu_Mobile.jpg",
        "updated": "03/04/2021"
    },
    {
        "name": "Những ngày vỡ đôi",
        "singer": "Đinh Uyên",
        "source": "../../assets/songs/NhungNgayVoDoi.mp3",
        "duration": "05:06",
        "thumbnail_desktop": "../../assets/thumbnails/desktop/NhungNgayVoDoi_Desktop.jpg",
        "thumbnail_mobile": "../../assets/thumbnails/mobile/NhungNgayVoDoi_Mobile.jpg",
        "updated": "03/04/2021"
    },
    {
        "name": "Anh đã quen với nỗi cô đơn",
        "singer": "Soobin Hoàng Sơn",
        "source": "../../assets/songs/AnhDaQuenVoiNoiCoDon.mp3",
        "duration": "03:56",
        "thumbnail_desktop": "../../assets/thumbnails/desktop/AnhDaQuenVoiNoiCoDon_Desktop.jpg",
        "thumbnail_mobile": "../../assets/thumbnails/mobile/AnhDaQuenVoiNoiCoDon_Mobile.jpg",
        "updated": "03/04/2021"
    },
    {
        "name": "Từ ngày em đến",
        "singer": "Da LAB",
        "source": "../../assets/songs/TuNgayEmDen.mp3",
        "duration": "04:24",
        "thumbnail_desktop": "../../assets/thumbnails/desktop/TuNgayEmDen_Desktop.jpg",
        "thumbnail_mobile": "../../assets/thumbnails/mobile/TuNgayEmDen_Mobile.jpg",
        "updated": "03/04/2021"
    }
]